{"chunk_definitions":[{"row":22,"row_count":1,"visible":true,"expansion_state":0,"options":{"engine":"r","echo":false,"message":false,"warning":false,"label":"unnamed-chunk-1"},"document_id":"2859484C","chunk_id":"c0up4ml1h1s50","chunk_label":"unnamed-chunk-1"},{"row":35,"row_count":1,"visible":true,"expansion_state":0,"options":{"engine":"r","echo":true,"message":false,"warning":false,"label":"unnamed-chunk-2"},"document_id":"2859484C","chunk_id":"c9h9uxxj1g2bw","chunk_label":"unnamed-chunk-2"}],"doc_write_time":1674002595}